{
  "author": "Neo",
  "data": [
    {
      "image": "sunday_at_the_park_page_02_image_0001.jpg",
      "page": 2,
      "text": [
        [
          {
            "narration": [
              {
                "audio": "we_are_in_cape_town_on_holiday.mp3",
                "from": 20,
                "segmentation": [
                  {
                    "end": 31,
                    "start": 20,
                    "word": "We"
                  },
                  {
                    "end": 54,
                    "start": 32,
                    "word": "are"
                  },
                  {
                    "end": 64,
                    "start": 55,
                    "word": "in"
                  },
                  {
                    "end": 91,
                    "start": 65,
                    "word": "Cape"
                  },
                  {
                    "end": 126,
                    "start": 92,
                    "word": "Town"
                  },
                  {
                    "end": 146,
                    "start": 127,
                    "word": "on"
                  },
                  {
                    "end": 199,
                    "start": 147,
                    "word": "holiday"
                  }
                ],
                "until": 199,
                "utterances": "We are in Cape Town on holiday"
              }
            ],
            "sentence": "We are in Cape Town on holiday."
          },
          {
            "narration": [
              {
                "audio": "we_are_excited_because_mom_and_dad_are_taking_us_to_the_park_next_to_the_sea.mp3",
                "from": 21,
                "segmentation": [
                  {
                    "end": 31,
                    "start": 21,
                    "word": "We"
                  },
                  {
                    "end": 50,
                    "start": 32,
                    "word": "are"
                  },
                  {
                    "end": 117,
                    "start": 51,
                    "word": "excited"
                  },
                  {
                    "end": 161,
                    "start": 118,
                    "word": "because"
                  },
                  {
                    "end": 193,
                    "start": 162,
                    "word": "Mom"
                  },
                  {
                    "end": 208,
                    "start": 194,
                    "word": "and"
                  },
                  {
                    "end": 222,
                    "start": 209,
                    "word": "Dad"
                  },
                  {
                    "end": 244,
                    "start": 223,
                    "word": "are"
                  },
                  {
                    "end": 309,
                    "start": 245,
                    "word": "taking"
                  },
                  {
                    "end": 330,
                    "start": 310,
                    "word": "us"
                  },
                  {
                    "end": 369,
                    "start": 331,
                    "word": "to"
                  },
                  {
                    "end": 379,
                    "start": 370,
                    "word": "the"
                  },
                  {
                    "end": 434,
                    "start": 380,
                    "word": "park"
                  },
                  {
                    "end": 473,
                    "start": 442,
                    "word": "next"
                  },
                  {
                    "end": 490,
                    "start": 474,
                    "word": "to"
                  },
                  {
                    "end": 501,
                    "start": 491,
                    "word": "the"
                  },
                  {
                    "end": 553,
                    "start": 502,
                    "word": "sea"
                  }
                ],
                "until": 553,
                "utterances": "We are excited because Mom and Dad are taking us to the park next to the sea"
              }
            ],
            "sentence": "We are excited because Mom and Dad are taking us to the park next to the sea."
          }
        ]
      ]
    },
    {
      "image": "sunday_at_the_park_page_03_image_0001.jpg",
      "page": 3,
      "text": [
        [
          {
            "narration": [
              {
                "audio": "look_at_the_tall_slide.mp3",
                "from": 19,
                "segmentation": [
                  {
                    "end": 45,
                    "start": 19,
                    "word": "Look"
                  },
                  {
                    "end": 52,
                    "start": 46,
                    "word": "at"
                  },
                  {
                    "end": 65,
                    "start": 53,
                    "word": "the"
                  },
                  {
                    "end": 116,
                    "start": 66,
                    "word": "tall"
                  },
                  {
                    "end": 184,
                    "start": 117,
                    "word": "slide"
                  }
                ],
                "until": 184,
                "utterances": "Look at the tall slide"
              }
            ],
            "sentence": "Look at the tall slide."
          },
          {
            "narration": [
              {
                "audio": "am_i_brave_enough_to_climb_up_and_slide_down.mp3",
                "from": 17,
                "segmentation": [
                  {
                    "end": 30,
                    "start": 17,
                    "word": "Am"
                  },
                  {
                    "end": 43,
                    "start": 31,
                    "word": "I"
                  },
                  {
                    "end": 85,
                    "start": 44,
                    "word": "brave"
                  },
                  {
                    "end": 116,
                    "start": 86,
                    "word": "enough"
                  },
                  {
                    "end": 128,
                    "start": 117,
                    "word": "to"
                  },
                  {
                    "end": 170,
                    "start": 129,
                    "word": "climb"
                  },
                  {
                    "end": 195,
                    "start": 171,
                    "word": "up"
                  },
                  {
                    "end": 208,
                    "start": 196,
                    "word": "and"
                  },
                  {
                    "end": 265,
                    "start": 209,
                    "word": "slide"
                  },
                  {
                    "end": 310,
                    "start": 266,
                    "word": "down"
                  }
                ],
                "until": 310,
                "utterances": "Am I brave enough to climb up and slide down"
              }
            ],
            "sentence": "Am I brave enough to climb up and slide down?"
          }
        ]
      ]
    },
    {
      "image": "sunday_at_the_park_page_04_image_0001.jpg",
      "page": 4,
      "text": [
        [
          {
            "narration": [
              {
                "audio": "my_sister_and_i_want_to_play_on_the_see_saw.mp3",
                "from": 19,
                "segmentation": [
                  {
                    "end": 28,
                    "start": 19,
                    "word": "My"
                  },
                  {
                    "end": 88,
                    "start": 29,
                    "word": "sister"
                  },
                  {
                    "end": 121,
                    "start": 89,
                    "word": "and"
                  },
                  {
                    "end": 124,
                    "start": 122,
                    "word": "I"
                  },
                  {
                    "end": 146,
                    "start": 125,
                    "word": "want"
                  },
                  {
                    "end": 154,
                    "start": 147,
                    "word": "to"
                  },
                  {
                    "end": 187,
                    "start": 155,
                    "word": "play"
                  },
                  {
                    "end": 206,
                    "start": 188,
                    "word": "on"
                  },
                  {
                    "end": 213,
                    "start": 207,
                    "word": "the"
                  },
                  {
                    "end": 247,
                    "start": 214,
                    "word": "see"
                  },
                  {
                    "end": 287,
                    "start": 248,
                    "word": "saw"
                  }
                ],
                "until": 287,
                "utterances": "My sister and I want to play on the see saw"
              }
            ],
            "sentence": "My sister and I want to play on the see saw."
          },
          {
            "narration": [
              {
                "audio": "i_wonder_which_one_of_us_is_heaviest.mp3",
                "from": 21,
                "segmentation": [
                  {
                    "end": 32,
                    "start": 21,
                    "word": "I"
                  },
                  {
                    "end": 67,
                    "start": 33,
                    "word": "wonder"
                  },
                  {
                    "end": 87,
                    "start": 68,
                    "word": "which"
                  },
                  {
                    "end": 108,
                    "start": 88,
                    "word": "one"
                  },
                  {
                    "end": 120,
                    "start": 109,
                    "word": "of"
                  },
                  {
                    "end": 140,
                    "start": 121,
                    "word": "us"
                  },
                  {
                    "end": 155,
                    "start": 141,
                    "word": "is"
                  },
                  {
                    "end": 229,
                    "start": 156,
                    "word": "heaviest"
                  }
                ],
                "until": 229,
                "utterances": "I wonder which one of us is heaviest"
              }
            ],
            "sentence": "I wonder which one of us is heaviest?"
          }
        ]
      ]
    },
    {
      "image": "sunday_at_the_park_page_05_image_0001.jpg",
      "page": 5,
      "text": [
        [
          {
            "narration": [
              {
                "audio": "mom_and_dad_need_to_push_us_when_we_want_to_swing.mp3",
                "from": 19,
                "segmentation": [
                  {
                    "end": 58,
                    "start": 19,
                    "word": "Mom"
                  },
                  {
                    "end": 76,
                    "start": 59,
                    "word": "and"
                  },
                  {
                    "end": 122,
                    "start": 77,
                    "word": "Dad"
                  },
                  {
                    "end": 142,
                    "start": 123,
                    "word": "need"
                  },
                  {
                    "end": 150,
                    "start": 143,
                    "word": "to"
                  },
                  {
                    "end": 187,
                    "start": 151,
                    "word": "push"
                  },
                  {
                    "end": 214,
                    "start": 188,
                    "word": "us"
                  },
                  {
                    "end": 235,
                    "start": 215,
                    "word": "when"
                  },
                  {
                    "end": 249,
                    "start": 236,
                    "word": "we"
                  },
                  {
                    "end": 279,
                    "start": 250,
                    "word": "want"
                  },
                  {
                    "end": 289,
                    "start": 280,
                    "word": "to"
                  },
                  {
                    "end": 329,
                    "start": 290,
                    "word": "swing"
                  }
                ],
                "until": 329,
                "utterances": "Mom and Dad need to push us when we want to swing"
              }
            ],
            "sentence": "Mom and Dad need to push us when we want to swing."
          },
          {
            "narration": [
              {
                "audio": "i_am_going_to_try_to_swing_the_highest.mp3",
                "from": 19,
                "segmentation": [
                  {
                    "end": 44,
                    "start": 19,
                    "word": "I"
                  },
                  {
                    "end": 58,
                    "start": 45,
                    "word": "am"
                  },
                  {
                    "end": 82,
                    "start": 59,
                    "word": "going"
                  },
                  {
                    "end": 94,
                    "start": 83,
                    "word": "to"
                  },
                  {
                    "end": 122,
                    "start": 95,
                    "word": "try"
                  },
                  {
                    "end": 141,
                    "start": 123,
                    "word": "to"
                  },
                  {
                    "end": 199,
                    "start": 142,
                    "word": "swing"
                  },
                  {
                    "end": 218,
                    "start": 200,
                    "word": "the"
                  },
                  {
                    "end": 331,
                    "start": 219,
                    "word": "highest"
                  }
                ],
                "until": 331,
                "utterances": "I am going to try to swing the highest"
              }
            ],
            "sentence": "I am going to try to swing the highest."
          }
        ]
      ]
    },
    {
      "image": "sunday_at_the_park_page_06_image_0001.jpg",
      "page": 6,
      "text": [
        [
          {
            "narration": [
              {
                "audio": "look_at_these_white_horses.mp3",
                "from": 19,
                "segmentation": [
                  {
                    "end": 47,
                    "start": 19,
                    "word": "Look"
                  },
                  {
                    "end": 59,
                    "start": 48,
                    "word": "at"
                  },
                  {
                    "end": 92,
                    "start": 60,
                    "word": "these"
                  },
                  {
                    "end": 133,
                    "start": 93,
                    "word": "white"
                  },
                  {
                    "end": 211,
                    "start": 134,
                    "word": "horses"
                  }
                ],
                "until": 211,
                "utterances": "Look at these white horses"
              }
            ],
            "sentence": "Look at these white horses."
          },
          {
            "narration": [
              {
                "audio": "they_are_statues.mp3",
                "from": 2,
                "segmentation": [
                  {
                    "end": 28,
                    "start": 2,
                    "word": "They"
                  },
                  {
                    "end": 46,
                    "start": 29,
                    "word": "are"
                  },
                  {
                    "end": 139,
                    "start": 47,
                    "word": "statues"
                  }
                ],
                "until": 139,
                "utterances": "They are statues"
              }
            ],
            "sentence": "They are statues."
          }
        ]
      ]
    },
    {
      "image": "sunday_at_the_park_page_07_image_0001.jpg",
      "page": 7,
      "text": [
        [
          {
            "narration": [
              {
                "audio": "we_read_the_sign_which_shows_us_what_fun_we_can_have_with_the_horses.mp3",
                "from": 21,
                "segmentation": [
                  {
                    "end": 31,
                    "start": 21,
                    "word": "We"
                  },
                  {
                    "end": 67,
                    "start": 32,
                    "word": "read"
                  },
                  {
                    "end": 75,
                    "start": 68,
                    "word": "the"
                  },
                  {
                    "end": 135,
                    "start": 76,
                    "word": "sign"
                  },
                  {
                    "end": 185,
                    "start": 170,
                    "word": "which"
                  },
                  {
                    "end": 219,
                    "start": 186,
                    "word": "shows"
                  },
                  {
                    "end": 240,
                    "start": 220,
                    "word": "us"
                  },
                  {
                    "end": 259,
                    "start": 241,
                    "word": "what"
                  },
                  {
                    "end": 289,
                    "start": 260,
                    "word": "fun"
                  },
                  {
                    "end": 307,
                    "start": 290,
                    "word": "we"
                  },
                  {
                    "end": 323,
                    "start": 308,
                    "word": "can"
                  },
                  {
                    "end": 370,
                    "start": 324,
                    "word": "have"
                  },
                  {
                    "end": 391,
                    "start": 371,
                    "word": "with"
                  },
                  {
                    "end": 400,
                    "start": 392,
                    "word": "the"
                  },
                  {
                    "end": 464,
                    "start": 401,
                    "word": "horses"
                  }
                ],
                "until": 464,
                "utterances": "We read the sign which shows us what fun we can have with the horses"
              }
            ],
            "sentence": "We read the sign which shows us what fun we can have with the horses."
          }
        ]
      ]
    },
    {
      "image": "sunday_at_the_park_page_08_image_0001.jpg",
      "page": 8,
      "text": [
        [
          {
            "narration": [
              {
                "audio": "we_visit_the_lighthouse.mp3",
                "from": 20,
                "segmentation": [
                  {
                    "end": 34,
                    "start": 20,
                    "word": "We"
                  },
                  {
                    "end": 73,
                    "start": 35,
                    "word": "visit"
                  },
                  {
                    "end": 85,
                    "start": 74,
                    "word": "the"
                  },
                  {
                    "end": 176,
                    "start": 86,
                    "word": "lighthouse"
                  }
                ],
                "until": 176,
                "utterances": "We visit the lighthouse"
              }
            ],
            "sentence": "We visit the lighthouse."
          },
          {
            "narration": [
              {
                "audio": "mom_and_dad_say_it_is_very_old.mp3",
                "from": 19,
                "segmentation": [
                  {
                    "end": 57,
                    "start": 19,
                    "word": "Mom"
                  },
                  {
                    "end": 74,
                    "start": 58,
                    "word": "and"
                  },
                  {
                    "end": 109,
                    "start": 75,
                    "word": "Dad"
                  },
                  {
                    "end": 127,
                    "start": 110,
                    "word": "say"
                  },
                  {
                    "end": 146,
                    "start": 128,
                    "word": "it"
                  },
                  {
                    "end": 203,
                    "start": 147,
                    "word": "is"
                  },
                  {
                    "end": 253,
                    "start": 204,
                    "word": "very"
                  },
                  {
                    "end": 287,
                    "start": 254,
                    "word": "old"
                  }
                ],
                "until": 287,
                "utterances": "Mom and Dad say it is very old"
              }
            ],
            "sentence": "Mom and Dad say it is very old."
          }
        ]
      ]
    },
    {
      "image": "sunday_at_the_park_page_09_image_0001.jpg",
      "page": 9,
      "text": [
        [
          {
            "narration": [
              {
                "audio": "lighthouses_are_important_at_night_and_in_the_fog.mp3",
                "from": 20,
                "segmentation": [
                  {
                    "end": 95,
                    "start": 20,
                    "word": "Lighthouses"
                  },
                  {
                    "end": 115,
                    "start": 96,
                    "word": "are"
                  },
                  {
                    "end": 175,
                    "start": 116,
                    "word": "important"
                  },
                  {
                    "end": 190,
                    "start": 176,
                    "word": "at"
                  },
                  {
                    "end": 242,
                    "start": 191,
                    "word": "night"
                  },
                  {
                    "end": 262,
                    "start": 243,
                    "word": "and"
                  },
                  {
                    "end": 277,
                    "start": 263,
                    "word": "in"
                  },
                  {
                    "end": 285,
                    "start": 278,
                    "word": "the"
                  },
                  {
                    "end": 357,
                    "start": 286,
                    "word": "fog"
                  }
                ],
                "until": 357,
                "utterances": "Lighthouses are important at night and in the fog"
              }
            ],
            "sentence": "Lighthouses are important at night and in the fog."
          },
          {
            "narration": [
              {
                "audio": "they_alert_ships_to_the_rocks_in_the_sea.mp3",
                "from": 19,
                "segmentation": [
                  {
                    "end": 28,
                    "start": 19,
                    "word": "They"
                  },
                  {
                    "end": 75,
                    "start": 29,
                    "word": "alert"
                  },
                  {
                    "end": 114,
                    "start": 76,
                    "word": "ships"
                  },
                  {
                    "end": 131,
                    "start": 115,
                    "word": "to"
                  },
                  {
                    "end": 140,
                    "start": 132,
                    "word": "the"
                  },
                  {
                    "end": 199,
                    "start": 141,
                    "word": "rocks"
                  },
                  {
                    "end": 213,
                    "start": 200,
                    "word": "in"
                  },
                  {
                    "end": 221,
                    "start": 214,
                    "word": "the"
                  },
                  {
                    "end": 240,
                    "start": 222,
                    "word": "sea"
                  }
                ],
                "until": 240,
                "utterances": "They alert ships to the rocks in the sea"
              }
            ],
            "sentence": "They alert ships to the rocks in the sea."
          }
        ]
      ]
    },
    {
      "image": "sunday_at_the_park_page_10_image_0001.jpg",
      "page": 10,
      "text": [
        [
          {
            "narration": [
              {
                "audio": "we_have_had_a_happy_time_at_the_park_but_now_it_is_home_time.mp3",
                "from": 21,
                "segmentation": [
                  {
                    "end": 33,
                    "start": 21,
                    "word": "We"
                  },
                  {
                    "end": 45,
                    "start": 34,
                    "word": "have"
                  },
                  {
                    "end": 68,
                    "start": 46,
                    "word": "had"
                  },
                  {
                    "end": 73,
                    "start": 69,
                    "word": "a"
                  },
                  {
                    "end": 117,
                    "start": 74,
                    "word": "happy"
                  },
                  {
                    "end": 162,
                    "start": 118,
                    "word": "time"
                  },
                  {
                    "end": 174,
                    "start": 163,
                    "word": "at"
                  },
                  {
                    "end": 181,
                    "start": 175,
                    "word": "the"
                  },
                  {
                    "end": 229,
                    "start": 182,
                    "word": "park"
                  },
                  {
                    "end": 268,
                    "start": 230,
                    "word": "but"
                  },
                  {
                    "end": 291,
                    "start": 269,
                    "word": "now"
                  },
                  {
                    "end": 322,
                    "start": 292,
                    "word": "it"
                  },
                  {
                    "end": 353,
                    "start": 323,
                    "word": "is"
                  },
                  {
                    "end": 401,
                    "start": 354,
                    "word": "home"
                  },
                  {
                    "end": 457,
                    "start": 402,
                    "word": "time"
                  }
                ],
                "until": 457,
                "utterances": "We have had a happy time at the park but now it is home time"
              }
            ],
            "sentence": "We have had a happy time at the park, but now it is home time."
          },
          {
            "narration": [
              {
                "audio": "we_are_going_to_catch_a_bus.mp3",
                "from": 17,
                "segmentation": [
                  {
                    "end": 34,
                    "start": 17,
                    "word": "We"
                  },
                  {
                    "end": 50,
                    "start": 35,
                    "word": "are"
                  },
                  {
                    "end": 83,
                    "start": 51,
                    "word": "going"
                  },
                  {
                    "end": 93,
                    "start": 84,
                    "word": "to"
                  },
                  {
                    "end": 126,
                    "start": 94,
                    "word": "catch"
                  },
                  {
                    "end": 132,
                    "start": 127,
                    "word": "a"
                  },
                  {
                    "end": 236,
                    "start": 133,
                    "word": "bus"
                  }
                ],
                "until": 236,
                "utterances": "We are going to catch a bus"
              }
            ],
            "sentence": "We are going to catch a bus."
          }
        ]
      ]
    },
    {
      "image": "sunday_at_the_park_page_11_image_0001.jpg",
      "page": 11,
      "text": [
        [
          {
            "narration": [
              {
                "audio": "thank_you_mom_and_dad_for_our_treat.mp3",
                "from": 2,
                "segmentation": [
                  {
                    "end": 48,
                    "start": 2,
                    "word": "Thank"
                  },
                  {
                    "end": 60,
                    "start": 49,
                    "word": "you"
                  },
                  {
                    "end": 92,
                    "start": 61,
                    "word": "Mom"
                  },
                  {
                    "end": 109,
                    "start": 93,
                    "word": "and"
                  },
                  {
                    "end": 147,
                    "start": 110,
                    "word": "Dad"
                  },
                  {
                    "end": 178,
                    "start": 148,
                    "word": "for"
                  },
                  {
                    "end": 217,
                    "start": 179,
                    "word": "our"
                  },
                  {
                    "end": 268,
                    "start": 218,
                    "word": "treat"
                  }
                ],
                "until": 268,
                "utterances": "Thank you Mom and Dad for our treat"
              }
            ],
            "sentence": "Thank you Mom and Dad for our treat."
          },
          {
            "narration": [
              {
                "audio": "we_are_tired_but_very_happy.mp3",
                "from": 20,
                "segmentation": [
                  {
                    "end": 31,
                    "start": 20,
                    "word": "We"
                  },
                  {
                    "end": 50,
                    "start": 32,
                    "word": "are"
                  },
                  {
                    "end": 107,
                    "start": 51,
                    "word": "tired"
                  },
                  {
                    "end": 135,
                    "start": 108,
                    "word": "but"
                  },
                  {
                    "end": 234,
                    "start": 136,
                    "word": "very"
                  },
                  {
                    "end": 290,
                    "start": 235,
                    "word": "happy"
                  }
                ],
                "until": 290,
                "utterances": "We are tired but very happy"
              }
            ],
            "sentence": "We are tired but very happy!"
          }
        ]
      ]
    }
  ],
  "level": "1",
  "title": "Sunday at the Park",
  "titleimage": "sunday_at_the_park_page_01_image_0001.jpg"
}